routerl/__init__.py
routerl/keychain.py
routerl/environment/__init__.py
routerl/environment/agent.py
routerl/environment/agent_generation.py
routerl/environment/environment.py
routerl/environment/observations.py
routerl/environment/params.json
routerl/environment/simulator.py
routerl/human_learning/__init__.py
routerl/human_learning/learning_model.py
routerl/human_learning/registry.py
routerl/networks/default_ods.json
routerl/networks/arterial/arterial.con.xml
routerl/networks/arterial/arterial.edg.xml
routerl/networks/arterial/arterial.net.xml
routerl/networks/arterial/arterial.nod.xml
routerl/networks/arterial/arterial.rou.xml
routerl/networks/arterial/arterial.sumocfg
routerl/networks/arterial/arterial.tll.xml
routerl/networks/arterial/arterial.typ.xml
routerl/networks/cologne/cologne.con.xml
routerl/networks/cologne/cologne.edg.xml
routerl/networks/cologne/cologne.net.xml
routerl/networks/cologne/cologne.nod.xml
routerl/networks/cologne/cologne.rou.xml
routerl/networks/cologne/cologne.sumocfg
routerl/networks/cologne/cologne.tll.xml
routerl/networks/cologne/cologne.typ.xml
routerl/networks/cologne/det.add.xml
routerl/networks/cologne/fcd.xml
routerl/networks/cologne/route.rou.xml
routerl/networks/cologne/summary.xml
routerl/networks/cologne/tripinfo.xml
routerl/networks/csomor/csomor.con.xml
routerl/networks/csomor/csomor.edg.xml
routerl/networks/csomor/csomor.net.xml
routerl/networks/csomor/csomor.nod.xml
routerl/networks/csomor/csomor.rou.xml
routerl/networks/csomor/csomor.sumocfg
routerl/networks/csomor/csomor.tll.xml
routerl/networks/csomor/csomor.typ.xml
routerl/networks/grid/grid.con.xml
routerl/networks/grid/grid.edg.xml
routerl/networks/grid/grid.net.xml
routerl/networks/grid/grid.nod.xml
routerl/networks/grid/grid.rou.xml
routerl/networks/grid/grid.sumocfg
routerl/networks/grid/grid.tll.xml
routerl/networks/grid6/grid6.con.xml
routerl/networks/grid6/grid6.edg.xml
routerl/networks/grid6/grid6.net.xml
routerl/networks/grid6/grid6.nod.xml
routerl-1.0.1.dist-info/licenses/LICENSE.txt
routerl-1.0.1.dist-info/METADATA
routerl-1.0.1.dist-info/WHEEL
routerl-1.0.1.dist-info/top_level.txt
routerl-1.0.1.dist-info/RECORD
