Metadata-Version: 2.4
Name: routerl
Version: 1.0.1
Summary: RouteRL is a multi-agent reinforcement learning framework for urban route choice in different city networks.
Author-email: COeXISTENCE <coexistence@uj.edu.pl>
License: MIT License
Project-URL: repository, https://github.com/COeXISTENCE-PROJECT/RouteRL
Project-URL: Bug Report, https://github.com/COeXISTENCE-PROJECT/RouteRL/issues
Keywords: routing,marl,transportation,rl,autonomous,vehicles,traffic
Classifier: Programming Language :: Python :: 3
Classifier: License :: OSI Approved :: MIT License
Classifier: Operating System :: OS Independent
Requires-Python: >=3.8
License-File: LICENSE.txt
Requires-Dist: gymnasium==1.0.0
Requires-Dist: janux>=1.0.0
Requires-Dist: matplotlib>=3.9.3
Requires-Dist: numpy>=2.0.2
Requires-Dist: pandas>=2.2.3
Requires-Dist: pettingzoo==1.24.3
Requires-Dist: polars==1.27.1
Requires-Dist: prettytable>=3.12.0
Requires-Dist: requests>=2.32.0
Requires-Dist: seaborn>=0.13.2
Requires-Dist: tensordict==0.7.0
Requires-Dist: torch>=2.6.0
Requires-Dist: torchrl==0.7.0
Requires-Dist: tqdm>=4.67.1
Requires-Dist: traci==1.21.0
Provides-Extra: dev
Requires-Dist: pytest>=8.3.4; extra == "dev"
Dynamic: license-file
